desktop_automation_recorder/__init__.py
desktop_automation_recorder/main.py
desktop_automation_recorder/gui/__init__.py
desktop_automation_recorder/gui/editor.py
desktop_automation_recorder/gui/feedback.py
desktop_automation_recorder/gui/main_window.py
desktop_automation_recorder/playback/__init__.py
desktop_automation_recorder/playback/player.py
desktop_automation_recorder/playback/preview.py
desktop_automation_recorder/recorder/__init__.py
desktop_automation_recorder/recorder/event_listener.py
desktop_automation_recorder/recorder/screenshot.py
desktop_automation_recorder/recorder/session.py
desktop_automation_recorder/scriptgen/__init__.py
desktop_automation_recorder/scriptgen/generator.py
desktop_automation_recorder/scriptgen/test_runner.py
desktop_automation_recorder/storage/__init__.py
desktop_automation_recorder/storage/formats.py
desktop_automation_recorder/storage/save_load.py
desktop_automation_recorder/utils/__init__.py
desktop_automation_recorder/utils/error_handling.py
desktop_automation_recorder/utils/hotkeys.py
desktop_automation_recorder/utils/image_compare.py
desktop_automation_recorder/utils/logger.py
gui/__init__.py
gui/editor.py
gui/feedback.py
gui/main_window.py
playback/__init__.py
playback/player.py
playback/preview.py
recorder/__init__.py
recorder/event_listener.py
recorder/screenshot.py
recorder/session.py
scriptgen/__init__.py
scriptgen/generator.py
scriptgen/test_runner.py
storage/__init__.py
storage/formats.py
storage/save_load.py
utils/__init__.py
utils/error_handling.py
utils/hotkeys.py
utils/image_compare.py
utils/logger.py
desktop_automation_recorder-0.1.1.dist-info/METADATA
desktop_automation_recorder-0.1.1.dist-info/WHEEL
desktop_automation_recorder-0.1.1.dist-info/entry_points.txt
desktop_automation_recorder-0.1.1.dist-info/top_level.txt
desktop_automation_recorder-0.1.1.dist-info/RECORD
